{
  "2018-12-09T00:00:00+00:00": {
    "Premier League": {
      "Newcastle v Wolves": {
        "time": "2018-12-09T16:00:00+00:00",
        "Teams": "Newcastle v Wolves",
        "3+": 1.2857142857142856,
        "4+": 1.8,
        "5+": 2.75
      }
    },
    "Copa Libertadores": {
      "River Plate v Boca Juniors": {
        "time": "2018-12-09T19:30:00+00:00",
        "Teams": "River Plate v Boca Juniors",
        "3+": 1.3636363636363638,
        "4+": 1.9090909090909092,
        "5+": 3.25
      }
    },
    "Spanish La Liga": {
      "Huesca v Real Madrid": {
        "time": "2018-12-09T15:15:00+00:00",
        "Teams": "Huesca v Real Madrid",
        "3+": 1.5,
        "4+": 2.1,
        "5+": 3.75
      },
      "Real Sociedad v Valladolid": {
        "time": "2018-12-09T17:30:00+00:00",
        "Teams": "Real Sociedad v Valladolid",
        "3+": 1.2857142857142856,
        "4+": 1.8,
        "5+": 2.875
      },
      "Betis v Rayo Vallecano": {
        "time": "2018-12-09T19:45:00+00:00",
        "Teams": "Betis v Rayo Vallecano",
        "3+": 1.3636363636363638,
        "4+": 2,
        "5+": 3.25
      }
    },
    "German Bundesliga": {
      "Borussia Monchengladbach v Stuttgart": {
        "time": "2018-12-09T17:00:00+00:00",
        "Teams": "Borussia Monchengladbach v Stuttgart",
        "3+": 1.2857142857142856,
        "4+": 1.8,
        "5+": 2.75
      }
    },
    "Italian Serie A": {
      "Genoa v SPAL": {
        "time": "2018-12-09T17:00:00+00:00",
        "Teams": "Genoa v SPAL",
        "3+": 1.3333333333333333,
        "4+": 1.9090909090909092,
        "5+": 3
      },
      "AC Milan v Torino": {
        "time": "2018-12-09T19:30:00+00:00",
        "Teams": "AC Milan v Torino",
        "3+": 1.2857142857142856,
        "4+": 1.8,
        "5+": 2.875
      }
    },
    "French Ligue 1": {
      "Lille v Stade Reims": {
        "time": "2018-12-09T16:00:00+00:00",
        "Teams": "Lille v Stade Reims",
        "3+": 1.5714285714285714,
        "4+": 2.5,
        "5+": 4
      }
    },
    "Belgian Jupiler League": {
      "Anderlecht v Sporting de Charleroi": {
        "time": "2018-12-09T17:00:00+00:00",
        "Teams": "Anderlecht v Sporting de Charleroi",
        "3+": 1.4,
        "4+": 2.1,
        "5+": 3.5
      },
      "Gent v KAS Eupen": {
        "time": "2018-12-09T19:00:00+00:00",
        "Teams": "Gent v KAS Eupen",
        "3+": 1.2857142857142856,
        "4+": 1.8,
        "5+": 2.75
      }
    },
    "Dutch Eredivisie": {
      "NAC Breda v Vitesse": {
        "time": "2018-12-09T15:45:00+00:00",
        "Teams": "NAC Breda v Vitesse",
        "3+": 1.4,
        "4+": 2,
        "5+": 3.25
      }
    },
    "Portuguese Super Liga": {
      "Moreirense FC v Santa Clara": {
        "time": "2018-12-09T15:00:00+00:00",
        "Teams": "Moreirense FC v Santa Clara",
        "3+": 1.3333333333333333,
        "4+": 1.8,
        "5+": 3
      },
      "Nacional da Madeira v Boavista FC": {
        "time": "2018-12-09T15:00:00+00:00",
        "Teams": "Nacional da Madeira v Boavista FC",
        "3+": 1.3333333333333333,
        "4+": 1.8,
        "5+": 3
      },
      "Vitoria de Guimaraes v Rio Ave": {
        "time": "2018-12-09T17:30:00+00:00",
        "Teams": "Vitoria de Guimaraes v Rio Ave",
        "3+": 1.2857142857142856,
        "4+": 1.8,
        "5+": 2.875
      },
      "Sporting CP v CD Aves": {
        "time": "2018-12-09T20:00:00+00:00",
        "Teams": "Sporting CP v CD Aves",
        "3+": 1.2857142857142856,
        "4+": 1.7272727272727273,
        "5+": 2.75
      }
    },
    "Russian Premier League": {
      "Zenit St Petersburg v Rubin Kazan": {
        "time": "2018-12-09T16:00:00+00:00",
        "Teams": "Zenit St Petersburg v Rubin Kazan",
        "3+": 1.5,
        "4+": 2.25,
        "5+": 3.75
      }
    },
    "Swiss Super League": {
      "FC Basel v FC Zurich": {
        "time": "2018-12-09T15:00:00+00:00",
        "Teams": "FC Basel v FC Zurich",
        "3+": 1.4,
        "4+": 2,
        "5+": 3.5
      },
      "Grasshoppers Zurich v FC Luzern": {
        "time": "2018-12-09T15:00:00+00:00",
        "Teams": "Grasshoppers Zurich v FC Luzern",
        "3+": 1.3636363636363638,
        "4+": 1.9090909090909092,
        "5+": 3.25
      },
      "Lugano v Sion": {
        "time": "2018-12-09T15:00:00+00:00",
        "Teams": "Lugano v Sion",
        "3+": 1.4,
        "4+": 2,
        "5+": 3.25
      }
    },
    "Turkish Super Lig": {
      "Akhisar Belediyespor v Fenerbahce": {
        "time": "2018-12-09T16:00:00+00:00",
        "Teams": "Akhisar Belediyespor v Fenerbahce",
        "3+": 1.5,
        "4+": 2.25,
        "5+": 4
      }
    },
    "Spanish Segunda": {
      "Cádiz v Rayo Majadahonda": {
        "time": "2018-12-09T15:00:00+00:00",
        "Teams": "Cádiz v Rayo Majadahonda",
        "3+": 1.5,
        "4+": 2.25,
        "5+": 4
      },
      "Elche CF v Sporting Gijon": {
        "time": "2018-12-09T17:00:00+00:00",
        "Teams": "Elche CF v Sporting Gijon",
        "3+": 1.3636363636363638,
        "4+": 2,
        "5+": 3.25
      },
      "Lugo v Las Palmas": {
        "time": "2018-12-09T19:00:00+00:00",
        "Teams": "Lugo v Las Palmas",
        "3+": 1.4,
        "4+": 2,
        "5+": 3.25
      },
      "Real Zaragoza v Cordoba": {
        "time": "2018-12-09T19:30:00+00:00",
        "Teams": "Real Zaragoza v Cordoba",
        "3+": 1.3333333333333333,
        "4+": 1.9090909090909092,
        "5+": 3
      }
    },
    "Italian Serie B": {
      "Benevento v Verona": {
        "time": "2018-12-09T20:00:00+00:00",
        "Teams": "Benevento v Verona",
        "3+": 1.3636363636363638,
        "4+": 1.9090909090909092,
        "5+": 3.25
      }
    },
    "Austrian Bundesliga": {
      "Rapid Vienna v Sturm Graz": {
        "time": "2018-12-09T16:00:00+00:00",
        "Teams": "Rapid Vienna v Sturm Graz",
        "3+": 1.3636363636363638,
        "4+": 2,
        "5+": 3.25
      }
    },
    "Danish Superliga": {
      "FC Copenhagen v Esbjerg": {
        "time": "2018-12-09T15:00:00+00:00",
        "Teams": "FC Copenhagen v Esbjerg",
        "3+": 1.3636363636363638,
        "4+": 1.9090909090909092,
        "5+": 3
      },
      "Vejle v Brøndby IF": {
        "time": "2018-12-09T17:00:00+00:00",
        "Teams": "Vejle v Brøndby IF",
        "3+": 1.3333333333333333,
        "4+": 1.8,
        "5+": 3
      }
    }
  },
  "2018-12-10T00:00:00+00:00": {
    "Premier League": {
      "Everton v Watford": {
        "time": "2018-12-10T20:00:00+00:00",
        "Teams": "Everton v Watford",
        "3+": 1.2857142857142856,
        "4+": 1.7272727272727273,
        "5+": 2.625
      }
    },
    "Spanish La Liga": {
      "Athletic Bilbao v Girona": {
        "time": "2018-12-10T20:00:00+00:00",
        "Teams": "Athletic Bilbao v Girona",
        "3+": 1.4444444444444444,
        "4+": 2.1,
        "5+": 3.75
      }
    },
    "Portuguese Super Liga": {
      "Feirense v Maritimo": {
        "time": "2018-12-10T20:15:00+00:00",
        "Teams": "Feirense v Maritimo",
        "3+": 1.4,
        "4+": 2.1,
        "5+": 3.5
      }
    },
    "Dutch Eerste Divisie": {
      "Jong AZ Alkmaar v Telstar": {
        "time": "2018-12-10T19:00:00+00:00",
        "Teams": "Jong AZ Alkmaar v Telstar",
        "3+": 1.3636363636363638,
        "4+": 1.9090909090909092,
        "5+": 3.25
      },
      "Jong PSV v Cambuur Leeuwarden": {
        "time": "2018-12-10T19:00:00+00:00",
        "Teams": "Jong PSV v Cambuur Leeuwarden",
        "3+": 1.3636363636363638,
        "4+": 1.9090909090909092,
        "5+": 3.25
      }
    }
  }
}